MANIFEST.in
Readme.rst
setup.py
CommonEnvironment/BitFlagEnum.py
CommonEnvironment/CallOnExit.py
CommonEnvironment/CommandLine.py
CommonEnvironment/Constraints.py
CommonEnvironment/FileSystem.py
CommonEnvironment/Interface.py
CommonEnvironment/Process.py
CommonEnvironment/RegularExpression.py
CommonEnvironment/StreamDecorator.py
CommonEnvironment/StringHelpers.py
CommonEnvironment/TaskPool.py
CommonEnvironment/TestTypeMetadata.py
CommonEnvironment/Visitor.py
CommonEnvironment/__init__.py
CommonEnvironment.egg-info/PKG-INFO
CommonEnvironment.egg-info/SOURCES.txt
CommonEnvironment.egg-info/dependency_links.txt
CommonEnvironment.egg-info/requires.txt
CommonEnvironment.egg-info/top_level.txt
CommonEnvironment/BuildImpl/DockerBuildImpl.py
CommonEnvironment/BuildImpl/PyPiBuildImpl.py
CommonEnvironment/BuildImpl/__init__.py
CommonEnvironment/CodeCoverageValidatorImpl/__init__.py
CommonEnvironment/CompilerImpl/CodeGenerator.py
CommonEnvironment/CompilerImpl/CommandLine.py
CommonEnvironment/CompilerImpl/Compiler.py
CommonEnvironment/CompilerImpl/Verifier.py
CommonEnvironment/CompilerImpl/__init__.py
CommonEnvironment/CompilerImpl/Impl/ConfigurationFileHelpers.py
CommonEnvironment/CompilerImpl/Impl/DistutilsCompilerImpl.py
CommonEnvironment/CompilerImpl/Impl/EnvironmentHelpers.py
CommonEnvironment/CompilerImpl/Impl/__init__.py
CommonEnvironment/CompilerImpl/InputProcessingMixin/AtomicInputProcessingMixin.py
CommonEnvironment/CompilerImpl/InputProcessingMixin/IndividualInputProcessingMixin.py
CommonEnvironment/CompilerImpl/InputProcessingMixin/__init__.py
CommonEnvironment/CompilerImpl/InvocationMixin/CommandLineInvocationMixin.py
CommonEnvironment/CompilerImpl/InvocationMixin/__init__.py
CommonEnvironment/CompilerImpl/InvocationQueryMixin/AlwaysInvocationQueryMixin.py
CommonEnvironment/CompilerImpl/InvocationQueryMixin/ConditionalInvocationQueryMixin.py
CommonEnvironment/CompilerImpl/InvocationQueryMixin/__init__.py
CommonEnvironment/CompilerImpl/OutputMixin/MultipleOutputMixin.py
CommonEnvironment/CompilerImpl/OutputMixin/NoOutputMixin.py
CommonEnvironment/CompilerImpl/OutputMixin/SingleOutputMixin.py
CommonEnvironment/CompilerImpl/OutputMixin/__init__.py
